setup.py
unfluff/__init__.py
unfluff/extraction.py
unfluff/graph.py
unfluff/main.py
unfluff/misc.py
unfluff/probability.py
unfluff.egg-info/PKG-INFO
unfluff.egg-info/SOURCES.txt
unfluff.egg-info/dependency_links.txt
unfluff.egg-info/entry_points.txt
unfluff.egg-info/requires.txt
unfluff.egg-info/top_level.txt
unfluff.egg-info/zip-safe