Metadata-Version: 1.0
Name: unfluff
Version: 0.2
Summary: HTML content extraction - remove the fluff
Home-page: http://github.com/gfxmonk/unfluff
Author: Tim Cuthbertson
Author-email: tim3d.junk+unfluff@gmail.com
License: BSD
Keywords: html content extraction
Platform: UNKNOWN
